Metadata-Version: 2.1
Name: techcombine
Version: 0.0.3
Summary: Techcombine framework for ecommerce
Home-page: https://github.com/chinnawatp/techcombine-framework
Maintainer: Techcombine developer team
Maintainer-email: chin@techcombine.co
License: MIT
Platform: any
Classifier: Development Status :: 4 - Beta
Classifier: Intended Audience :: Developers
Classifier: Operating System :: OS Independent
Classifier: Programming Language :: Python :: 3
Classifier: Programming Language :: Python :: 3.4
Classifier: Programming Language :: Python :: 3.5
Classifier: Programming Language :: Python :: 3.6
Classifier: Programming Language :: Python :: 3.7
Classifier: Topic :: Software Development :: Build Tools
Classifier: License :: OSI Approved :: MIT License
Requires-Python: >=3.6.1
Provides-Extra: dev
